icetea-2.0.1.data/data/icetea_lib/logging_schema.json
icetea-2.0.1.data/data/icetea_lib/tc_schema.json
icetea_lib/AllocationContext.py
icetea_lib/CliAsyncResponse.py
icetea_lib/CliRequest.py
icetea_lib/CliResponse.py
icetea_lib/CliResponseParser.py
icetea_lib/IceteaManager.py
icetea_lib/LogManager.py
icetea_lib/Result.py
icetea_lib/ResultList.py
icetea_lib/ReturnCodes.py
icetea_lib/Searcher.py
icetea_lib/TestStepError.py
icetea_lib/__init__.py
icetea_lib/arguments.py
icetea_lib/bench.py
icetea_lib/cloud.py
icetea_lib/enhancedserial.py
icetea_lib/logging_schema.json
icetea_lib/main.py
icetea_lib/tc_schema.json
icetea_lib/timer.py
icetea_lib/wireshark.py
icetea_lib/DeviceConnectors/Dut.py
icetea_lib/DeviceConnectors/DutInformation.py
icetea_lib/DeviceConnectors/__init__.py
icetea_lib/Events/EventMatch.py
icetea_lib/Events/EventMatcher.py
icetea_lib/Events/Generics.py
icetea_lib/Events/__init__.py
icetea_lib/Plugin/PluginBase.py
icetea_lib/Plugin/PluginManager.py
icetea_lib/Plugin/__init__.py
icetea_lib/Plugin/plugins/Asserts.py
icetea_lib/Plugin/plugins/FileApi.py
icetea_lib/Plugin/plugins/HttpApi.py
icetea_lib/Plugin/plugins/__init__.py
icetea_lib/Plugin/plugins/default_parsers.py
icetea_lib/Plugin/plugins/default_plugins.py
icetea_lib/Plugin/plugins/plugin_localallocator.py
icetea_lib/Plugin/plugins/plugins_to_load.py
icetea_lib/Plugin/plugins/LocalAllocator/DutConsole.py
icetea_lib/Plugin/plugins/LocalAllocator/DutDetection.py
icetea_lib/Plugin/plugins/LocalAllocator/DutMbed.py
icetea_lib/Plugin/plugins/LocalAllocator/DutProcess.py
icetea_lib/Plugin/plugins/LocalAllocator/DutSerial.py
icetea_lib/Plugin/plugins/LocalAllocator/DutTcp.py
icetea_lib/Plugin/plugins/LocalAllocator/LocalAllocator.py
icetea_lib/Plugin/plugins/LocalAllocator/__init__.py
icetea_lib/Plugin/plugins/plugin_tests/__init__.py
icetea_lib/Plugin/plugins/plugin_tests/test_dutmbed.py
icetea_lib/Plugin/plugins/plugin_tests/test_dutserial.py
icetea_lib/Plugin/plugins/plugin_tests/test_httpapi.py
icetea-2.0.1.dist-info/LICENSE
icetea-2.0.1.dist-info/METADATA
icetea-2.0.1.dist-info/WHEEL
icetea-2.0.1.dist-info/entry_points.txt
icetea-2.0.1.dist-info/top_level.txt
icetea-2.0.1.dist-info/RECORD
