Metadata-Version: 2.1
Name: icetea
Version: 2.0.1
Summary: Icetea - test framework
Home-page: https://github.com/ARMmbed/icetea.git
Author: Joonas Nikula
Author-email: oulab.mbedcloudtesting.com@arm.com
Maintainer: Joonas Nikula
Maintainer-email: oulab.mbedcloudtesting.com@arm.com
License: (R) ARM
Keywords: armbed mbed-os mbed-cli ci framework testing automation
Platform: UNKNOWN
Classifier: Programming Language :: Python :: 2.7
Classifier: Programming Language :: Python :: 3.5
Classifier: Programming Language :: Python :: 3.6
Classifier: Programming Language :: Python :: 3.7
Classifier: License :: OSI Approved :: Apache Software License
Classifier: Operating System :: OS Independent
Requires-Dist: prettytable (<1.0)
Requires-Dist: requests
Requires-Dist: yattag (<2.0,>=1.0)
Requires-Dist: pyserial (>2.5)
Requires-Dist: jsonmerge (<2.0,>=1.4.0)
Requires-Dist: jsonschema (<3.0.0)
Requires-Dist: mbed-ls (<2.0,>=1.5.1)
Requires-Dist: semver (<3.0,>=2.0)
Requires-Dist: mbed-flasher (<0.11,>=0.10.1)
Requires-Dist: six (<2.0,>=1.0)
Requires-Dist: pydash (<5.0,>=4.0)
Requires-Dist: transitions (<1.0)
